tglcourse/__init__.py
tglcourse/_modidx.py
tglcourse/data_utils.py
tglcourse/generation_utils.py
tglcourse/lesson12.py
tglcourse/utils.py
tglcourse-0.0.5.dist-info/LICENSE
tglcourse-0.0.5.dist-info/METADATA
tglcourse-0.0.5.dist-info/WHEEL
tglcourse-0.0.5.dist-info/entry_points.txt
tglcourse-0.0.5.dist-info/top_level.txt
tglcourse-0.0.5.dist-info/RECORD
