Metadata-Version: 2.1
Name: tglcourse
Version: 0.0.5
Summary: work-in-progress course
Home-page: https://github.com/johnowhitaker/tglcourse/
Author: Jonathan Whitaker
Author-email: johnowhitaker@gmail.com
License: Apache Software License 2.0
Keywords: generative
Classifier: Development Status :: 3 - Alpha
Classifier: Intended Audience :: Developers
Classifier: Natural Language :: English
Classifier: Programming Language :: Python :: 3.7
Classifier: Programming Language :: Python :: 3.8
Classifier: Programming Language :: Python :: 3.9
Classifier: Programming Language :: Python :: 3.10
Classifier: License :: OSI Approved :: Apache Software License
Requires-Python: >=3.7
License-File: LICENSE
Requires-Dist: torch
Requires-Dist: torchvision
Requires-Dist: pillow
Requires-Dist: matplotlib
Requires-Dist: tqdm
Requires-Dist: ipywidgets
Requires-Dist: huggingface-hub
Requires-Dist: transformers
Requires-Dist: diffusers
Requires-Dist: datasets
Requires-Dist: imstack
Requires-Dist: open-clip-torch
Requires-Dist: siren-pytorch
Requires-Dist: fastcore
Requires-Dist: fastai
Requires-Dist: librosa
Requires-Dist: soundfile
Requires-Dist: wandb
Requires-Dist: gradio
Provides-Extra: dev
